deepseek_r1/__main__.py
deepseek_r1/r1.py
deepseek_r1-0.1.0.dist-info/METADATA
deepseek_r1-0.1.0.dist-info/WHEEL
deepseek_r1-0.1.0.dist-info/top_level.txt
deepseek_r1-0.1.0.dist-info/RECORD
